argparse_utilities/__init__.py
argparse_utilities/argparse_utilities.py
argparse_utilities-0.0.2.dist-info/LICENSE
argparse_utilities-0.0.2.dist-info/METADATA
argparse_utilities-0.0.2.dist-info/WHEEL
argparse_utilities-0.0.2.dist-info/top_level.txt
argparse_utilities-0.0.2.dist-info/RECORD
